sft/__init__.py
sft/_build_info.py
sft/cli.py
sft/server.py
simple_file_transfer-0.2.2.dist-info/licenses/LICENSE
tests/__init__.py
tests/test_cli.py
tests/test_server.py
tests/e2e/__init__.py
tests/e2e/run_e2e_tests.sh
simple_file_transfer-0.2.2.dist-info/METADATA
simple_file_transfer-0.2.2.dist-info/WHEEL
simple_file_transfer-0.2.2.dist-info/entry_points.txt
simple_file_transfer-0.2.2.dist-info/top_level.txt
simple_file_transfer-0.2.2.dist-info/RECORD
