Metadata-Version: 2.4
Name: simple-file-transfer
Version: 0.2.2
Summary: A simple file transfer service for temporary file sharing
Author: Simple File Transfer
License: MIT
Project-URL: Homepage, https://github.com/yourusername/simple-file-transfer
Classifier: Development Status :: 3 - Alpha
Classifier: Intended Audience :: Developers
Classifier: License :: OSI Approved :: MIT License
Classifier: Programming Language :: Python :: 3
Classifier: Programming Language :: Python :: 3.8
Classifier: Programming Language :: Python :: 3.9
Classifier: Programming Language :: Python :: 3.10
Classifier: Programming Language :: Python :: 3.11
Requires-Python: >=3.8
License-File: LICENSE
Requires-Dist: flask>=2.3.0
Requires-Dist: click>=8.1.0
Requires-Dist: requests>=2.31.0
Dynamic: license-file
Dynamic: requires-python
